odoo10_addon_stock_picking_variant_mgmt-10.0.1.0.0-py2.7-nspkg.pth
odoo/addons/stock_picking_variant_mgmt/README.rst
odoo/addons/stock_picking_variant_mgmt/__init__.py
odoo/addons/stock_picking_variant_mgmt/__manifest__.py
odoo/addons/stock_picking_variant_mgmt/i18n/es.po
odoo/addons/stock_picking_variant_mgmt/i18n/it.po
odoo/addons/stock_picking_variant_mgmt/models/__init__.py
odoo/addons/stock_picking_variant_mgmt/models/stock_move.py
odoo/addons/stock_picking_variant_mgmt/static/description/icon.png
odoo/addons/stock_picking_variant_mgmt/tests/__init__.py
odoo/addons/stock_picking_variant_mgmt/tests/test_stock_picking_variant_mgmt.py
odoo/addons/stock_picking_variant_mgmt/views/stock_picking_view.xml
odoo/addons/stock_picking_variant_mgmt/wizard/__init__.py
odoo/addons/stock_picking_variant_mgmt/wizard/stock_manage_variant.py
odoo/addons/stock_picking_variant_mgmt/wizard/stock_manage_variant_view.xml
odoo/addons/stock_picking_variant_mgmt/wizard/stock_transfer_manage_variant.py
odoo/addons/stock_picking_variant_mgmt/wizard/stock_transfer_manage_variant_view.xml
odoo10_addon_stock_picking_variant_mgmt-10.0.1.0.0.dist-info/DESCRIPTION.rst
odoo10_addon_stock_picking_variant_mgmt-10.0.1.0.0.dist-info/METADATA
odoo10_addon_stock_picking_variant_mgmt-10.0.1.0.0.dist-info/RECORD
odoo10_addon_stock_picking_variant_mgmt-10.0.1.0.0.dist-info/WHEEL
odoo10_addon_stock_picking_variant_mgmt-10.0.1.0.0.dist-info/metadata.json
odoo10_addon_stock_picking_variant_mgmt-10.0.1.0.0.dist-info/namespace_packages.txt
odoo10_addon_stock_picking_variant_mgmt-10.0.1.0.0.dist-info/top_level.txt
